pynerator/__init__.py
pynerator/__main__.py
pynerator/pynerator_ui.py
pynerator/pyneratorgui.py
pynerator-1.0.0.dist-info/LICENSE
pynerator-1.0.0.dist-info/METADATA
pynerator-1.0.0.dist-info/WHEEL
pynerator-1.0.0.dist-info/top_level.txt
pynerator-1.0.0.dist-info/RECORD
